{
  "status": "NORMAL",
  "outlookText": "Critical Weather Day is not currently expected in the next 3 days. However, NCO is monitoring Tropical Depression Two off the west coast of Florida along with severe storm concerns from the Midwest and Great Lakes to the Ohio Valley early this week.",
  "days": [
    {
      "weekday": "Sun",
      "date": "Jul 19",
      "status": "Enhanced Caution",
      "hazards": [
        "idss"
      ]
    },
    {
      "weekday": "Mon",
      "date": "Jul 20",
      "status": "Enhanced Caution",
      "hazards": [
        "lightning",
        "tropical"
      ]
    },
    {
      "weekday": "Tue",
      "date": "Jul 21",
      "status": "Enhanced Caution",
      "hazards": [
        "lightning",
        "tropical"
      ]
    }
  ],
  "updated": "2026-07-19T23:02:35Z"
}